README.md
setup.py
hashmap_data_cataloger.egg-info/PKG-INFO
hashmap_data_cataloger.egg-info/SOURCES.txt
hashmap_data_cataloger.egg-info/dependency_links.txt
hashmap_data_cataloger.egg-info/entry_points.txt
hashmap_data_cataloger.egg-info/requires.txt
hashmap_data_cataloger.egg-info/top_level.txt
hdc/__init__.py
hdc/__main__.py
hdc/core/__init__.py
hdc/core/asset_mapper.py
hdc/core/cataloger.py
hdc/core/catalog/__init__.py
hdc/core/catalog/crawler.py
hdc/core/catalog/hdfs_crawler.py
hdc/core/catalog/hive_crawler.py
hdc/core/catalog/netezza_crawler.py
hdc/core/catalog/oracle_crawler.py
hdc/core/catalog/rdbms_crawler.py
hdc/core/create/__init__.py
hdc/core/create/creator.py
hdc/core/create/rdbms_creator.py
hdc/core/create/snowflake_creator.py
hdc/core/dao/__init__.py
hdc/core/dao/dao.py
hdc/core/dao/filesystem_dao.py
hdc/core/dao/hdfs.py
hdc/core/dao/hive.py
hdc/core/dao/jdbc_connector.py
hdc/core/dao/netezza.py
hdc/core/dao/odbc_connector.py
hdc/core/dao/oracle.py
hdc/core/dao/rdbms_dao.py
hdc/core/dao/snowflake.py
hdc/core/exceptions/__init__.py
hdc/core/exceptions/hdc_error.py
hdc/core/map/__init__.py
hdc/core/map/hdfs_to_snowflake.py
hdc/core/map/hive_to_snowflake.py
hdc/core/map/mapper.py
hdc/core/map/mapper_reporting.py
hdc/core/map/netezza_to_snowflake.py
hdc/core/map/oracle_to_snowflake.py
hdc/utils/__init__.py
hdc/utils/file_utils.py
hdc/utils/markdown_utils.py
tests/__init__.py
tests/core/__init__.py
tests/core/crawler/__init__.py
tests/core/crawler/test_hdfs_crawler.py
tests/core/crawler/test_hive_crawler.py
tests/core/crawler/test_netezza_crawler.py
tests/core/crawler/test_oracle_crawler.py
tests/core/creator/__init__.py
tests/core/creator/test_snowflake_creator.py
tests/core/mapper/__init__.py
tests/core/mapper/test_hdfs_to_snowflake.py
tests/core/mapper/test_hive_to_snowflake.py
tests/core/mapper/test_netezza_to_snowflake.py
tests/core/mapper/test_oracle_to_snowflake.py