Metadata-Version: 2.1
Name: hashmap-data-cataloger
Version: 0.3.0.0
Summary: Early version of library - do not use
Home-page: https://gitlab.com/hashmapinc/oss/hashmap_data_cataloger
Author: Hashmap, an NTT DATA Company
Author-email: accelerators@hashmapinc.com
License: UNKNOWN
Platform: UNKNOWN
Classifier: Programming Language :: Python :: 3
Classifier: License :: OSI Approved :: Apache Software License
Classifier: Operating System :: OS Independent
Classifier: Development Status :: 4 - Beta
Requires-Python: >=3.6
